AisacTaxiiClient/__init__.py
AisacTaxiiClient-0.9.3.dist-info/METADATA
AisacTaxiiClient-0.9.3.dist-info/RECORD
AisacTaxiiClient-0.9.3.dist-info/WHEEL
AisacTaxiiClient-0.9.3.dist-info/entry_points.txt
AisacTaxiiClient-0.9.3.dist-info/top_level.txt
