Metadata-Version: 2.1
Name: AisacTaxiiClient
Version: 0.9.3
Summary: SDK for aisac taxii server
Home-page: https://github.com/cjltsod/AisacTaxiiClient
Author: Chun-Jung Lee
Author-email: aisac_taxii_client.tsod@tsod.idv.tw
License: MIT
Keywords: taxii aisac client sdk
Platform: UNKNOWN
Classifier: Development Status :: 4 - Beta
Classifier: Intended Audience :: Developers
Classifier: Topic :: Software Development :: Build Tools
Classifier: License :: OSI Approved :: MIT License
Classifier: Programming Language :: Python :: 3
Classifier: Programming Language :: Python :: 3.6
Requires-Dist: cabby
